{"info":{"file":"public/javascripts/search.js","fileShort":"public/javascripts/search.js","fileSafe":"public_javascripts_search_js","link":"files/public_javascripts_search_js/index.html"},"complexity":{"aggregate":{"sloc":{"logical":275,"physical":409},"cyclomatic":38,"halstead":{"operators":{"distinct":21,"total":773,"identifiers":["__stripped__"]},"operands":{"distinct":182,"total":909,"identifiers":["__stripped__"]},"length":1682,"vocabulary":203,"difficulty":52.44230769230769,"volume":12893.095012705468,"effort":676143.6557624579,"bugs":4.297698337568489,"time":37563.53643124766},"params":8,"line":9,"cyclomaticDensity":13.818181818181818,"complexity":{"cyclomatic":38,"sloc":{"logical":275,"physical":409},"halstead":{"operators":{"distinct":21,"total":773,"identifiers":["__stripped__"]},"operands":{"distinct":182,"total":909,"identifiers":["__stripped__"]},"length":1682,"vocabulary":203,"difficulty":52.44230769230769,"volume":12893.095012705468,"effort":676143.6557624579,"bugs":4.297698337568489,"time":37563.53643124766}}},"functions":[{"name":"<anonymous>","sloc":{"logical":3,"physical":8},"cyclomatic":1,"halstead":{"operators":{"distinct":4,"total":10,"identifiers":["__stripped__"]},"operands":{"distinct":7,"total":10,"identifiers":["__stripped__"]},"length":20,"vocabulary":11,"difficulty":2.857142857142857,"volume":69.18863237274596,"effort":197.68180677927415,"bugs":0.023062877457581985,"time":10.982322598848564},"params":0,"line":26,"cyclomaticDensity":33.33333333333333,"complexity":{"cyclomatic":1,"sloc":{"logical":3,"physical":8},"halstead":{"operators":{"distinct":4,"total":10,"identifiers":["__stripped__"]},"operands":{"distinct":7,"total":10,"identifiers":["__stripped__"]},"length":20,"vocabulary":11,"difficulty":2.857142857142857,"volume":69.18863237274596,"effort":197.68180677927415,"bugs":0.023062877457581985,"time":10.982322598848564}}},{"name":"<anonymous>","sloc":{"logical":4,"physical":10},"cyclomatic":2,"halstead":{"operators":{"distinct":5,"total":8,"identifiers":["__stripped__"]},"operands":{"distinct":4,"total":9,"identifiers":["__stripped__"]},"length":17,"vocabulary":9,"difficulty":5.625,"volume":53.88872502451932,"effort":303.12407826292116,"bugs":0.017962908341506437,"time":16.840226570162287},"params":0,"line":37,"cyclomaticDensity":50,"complexity":{"cyclomatic":2,"sloc":{"logical":4,"physical":10},"halstead":{"operators":{"distinct":5,"total":8,"identifiers":["__stripped__"]},"operands":{"distinct":4,"total":9,"identifiers":["__stripped__"]},"length":17,"vocabulary":9,"difficulty":5.625,"volume":53.88872502451932,"effort":303.12407826292116,"bugs":0.017962908341506437,"time":16.840226570162287}}},{"name":"<anonymous>","sloc":{"logical":4,"physical":7},"cyclomatic":2,"halstead":{"operators":{"distinct":5,"total":8,"identifiers":["__stripped__"]},"operands":{"distinct":4,"total":9,"identifiers":["__stripped__"]},"length":17,"vocabulary":9,"difficulty":5.625,"volume":53.88872502451932,"effort":303.12407826292116,"bugs":0.017962908341506437,"time":16.840226570162287},"params":0,"line":49,"cyclomaticDensity":50,"complexity":{"cyclomatic":2,"sloc":{"logical":4,"physical":7},"halstead":{"operators":{"distinct":5,"total":8,"identifiers":["__stripped__"]},"operands":{"distinct":4,"total":9,"identifiers":["__stripped__"]},"length":17,"vocabulary":9,"difficulty":5.625,"volume":53.88872502451932,"effort":303.12407826292116,"bugs":0.017962908341506437,"time":16.840226570162287}}},{"name":"<anonymous>","sloc":{"logical":33,"physical":47},"cyclomatic":4,"halstead":{"operators":{"distinct":12,"total":89,"identifiers":["__stripped__"]},"operands":{"distinct":55,"total":106,"identifiers":["__stripped__"]},"length":195,"vocabulary":67,"difficulty":11.563636363636363,"volume":1182.8873921392656,"effort":13678.479661828596,"bugs":0.3942957973797552,"time":759.9155367682554},"params":0,"line":63,"cyclomaticDensity":12.121212121212121,"complexity":{"cyclomatic":4,"sloc":{"logical":33,"physical":47},"halstead":{"operators":{"distinct":12,"total":89,"identifiers":["__stripped__"]},"operands":{"distinct":55,"total":106,"identifiers":["__stripped__"]},"length":195,"vocabulary":67,"difficulty":11.563636363636363,"volume":1182.8873921392656,"effort":13678.479661828596,"bugs":0.3942957973797552,"time":759.9155367682554}}},{"name":"<anonymous>","sloc":{"logical":33,"physical":45},"cyclomatic":4,"halstead":{"operators":{"distinct":12,"total":89,"identifiers":["__stripped__"]},"operands":{"distinct":55,"total":106,"identifiers":["__stripped__"]},"length":195,"vocabulary":67,"difficulty":11.563636363636363,"volume":1182.8873921392656,"effort":13678.479661828596,"bugs":0.3942957973797552,"time":759.9155367682554},"params":0,"line":114,"cyclomaticDensity":12.121212121212121,"complexity":{"cyclomatic":4,"sloc":{"logical":33,"physical":45},"halstead":{"operators":{"distinct":12,"total":89,"identifiers":["__stripped__"]},"operands":{"distinct":55,"total":106,"identifiers":["__stripped__"]},"length":195,"vocabulary":67,"difficulty":11.563636363636363,"volume":1182.8873921392656,"effort":13678.479661828596,"bugs":0.3942957973797552,"time":759.9155367682554}}},{"name":"<anonymous>","sloc":{"logical":33,"physical":44},"cyclomatic":4,"halstead":{"operators":{"distinct":12,"total":89,"identifiers":["__stripped__"]},"operands":{"distinct":55,"total":106,"identifiers":["__stripped__"]},"length":195,"vocabulary":67,"difficulty":11.563636363636363,"volume":1182.8873921392656,"effort":13678.479661828596,"bugs":0.3942957973797552,"time":759.9155367682554},"params":0,"line":162,"cyclomaticDensity":12.121212121212121,"complexity":{"cyclomatic":4,"sloc":{"logical":33,"physical":44},"halstead":{"operators":{"distinct":12,"total":89,"identifiers":["__stripped__"]},"operands":{"distinct":55,"total":106,"identifiers":["__stripped__"]},"length":195,"vocabulary":67,"difficulty":11.563636363636363,"volume":1182.8873921392656,"effort":13678.479661828596,"bugs":0.3942957973797552,"time":759.9155367682554}}},{"name":"change_comparison","sloc":{"logical":29,"physical":34},"cyclomatic":6,"halstead":{"operators":{"distinct":10,"total":51,"identifiers":["__stripped__"]},"operands":{"distinct":34,"total":67,"identifiers":["__stripped__"]},"length":118,"vocabulary":44,"difficulty":9.852941176470589,"volume":644.212930999201,"effort":6347.392114256834,"bugs":0.21473764366640036,"time":352.6328952364908},"params":2,"line":210,"cyclomaticDensity":20.689655172413794,"complexity":{"cyclomatic":6,"sloc":{"logical":29,"physical":34},"halstead":{"operators":{"distinct":10,"total":51,"identifiers":["__stripped__"]},"operands":{"distinct":34,"total":67,"identifiers":["__stripped__"]},"length":118,"vocabulary":44,"difficulty":9.852941176470589,"volume":644.212930999201,"effort":6347.392114256834,"bugs":0.21473764366640036,"time":352.6328952364908}}},{"name":"showMetadataHint","sloc":{"logical":12,"physical":42},"cyclomatic":3,"halstead":{"operators":{"distinct":11,"total":26,"identifiers":["__stripped__"]},"operands":{"distinct":21,"total":29,"identifiers":["__stripped__"]},"length":55,"vocabulary":32,"difficulty":7.595238095238095,"volume":275,"effort":2088.690476190476,"bugs":0.09166666666666666,"time":116.03835978835978},"params":1,"line":247,"cyclomaticDensity":25,"complexity":{"cyclomatic":3,"sloc":{"logical":12,"physical":42},"halstead":{"operators":{"distinct":11,"total":26,"identifiers":["__stripped__"]},"operands":{"distinct":21,"total":29,"identifiers":["__stripped__"]},"length":55,"vocabulary":32,"difficulty":7.595238095238095,"volume":275,"effort":2088.690476190476,"bugs":0.09166666666666666,"time":116.03835978835978}}},{"name":"xmlhttp.onreadystatechange","sloc":{"logical":13,"physical":26},"cyclomatic":3,"halstead":{"operators":{"distinct":11,"total":33,"identifiers":["__stripped__"]},"operands":{"distinct":24,"total":40,"identifiers":["__stripped__"]},"length":73,"vocabulary":35,"difficulty":9.166666666666668,"volume":374.43766023698254,"effort":3432.345218839007,"bugs":0.12481255341232751,"time":190.68584549105594},"params":0,"line":259,"cyclomaticDensity":23.076923076923077,"complexity":{"cyclomatic":3,"sloc":{"logical":13,"physical":26},"halstead":{"operators":{"distinct":11,"total":33,"identifiers":["__stripped__"]},"operands":{"distinct":24,"total":40,"identifiers":["__stripped__"]},"length":73,"vocabulary":35,"difficulty":9.166666666666668,"volume":374.43766023698254,"effort":3432.345218839007,"bugs":0.12481255341232751,"time":190.68584549105594}}},{"name":"showTaxResult","sloc":{"logical":20,"physical":34},"cyclomatic":3,"halstead":{"operators":{"distinct":10,"total":62,"identifiers":["__stripped__"]},"operands":{"distinct":33,"total":74,"identifiers":["__stripped__"]},"length":136,"vocabulary":43,"difficulty":11.212121212121211,"volume":737.9720066394854,"effort":8274.231589594228,"bugs":0.24599066887982846,"time":459.6795327552349},"params":1,"line":292,"cyclomaticDensity":15,"complexity":{"cyclomatic":3,"sloc":{"logical":20,"physical":34},"halstead":{"operators":{"distinct":10,"total":62,"identifiers":["__stripped__"]},"operands":{"distinct":33,"total":74,"identifiers":["__stripped__"]},"length":136,"vocabulary":43,"difficulty":11.212121212121211,"volume":737.9720066394854,"effort":8274.231589594228,"bugs":0.24599066887982846,"time":459.6795327552349}}},{"name":"xmlhttp.onreadystatechange","sloc":{"logical":6,"physical":9},"cyclomatic":2,"halstead":{"operators":{"distinct":6,"total":31,"identifiers":["__stripped__"]},"operands":{"distinct":19,"total":36,"identifiers":["__stripped__"]},"length":67,"vocabulary":25,"difficulty":5.684210526315789,"volume":311.1383647149065,"effort":1768.5759678531529,"bugs":0.10371278823830217,"time":98.25422043628627},"params":0,"line":314,"cyclomaticDensity":33.33333333333333,"complexity":{"cyclomatic":2,"sloc":{"logical":6,"physical":9},"halstead":{"operators":{"distinct":6,"total":31,"identifiers":["__stripped__"]},"operands":{"distinct":19,"total":36,"identifiers":["__stripped__"]},"length":67,"vocabulary":25,"difficulty":5.684210526315789,"volume":311.1383647149065,"effort":1768.5759678531529,"bugs":0.10371278823830217,"time":98.25422043628627}}},{"name":"showUserResult","sloc":{"logical":13,"physical":33},"cyclomatic":3,"halstead":{"operators":{"distinct":10,"total":34,"identifiers":["__stripped__"]},"operands":{"distinct":25,"total":39,"identifiers":["__stripped__"]},"length":73,"vocabulary":35,"difficulty":7.800000000000001,"volume":374.43766023698254,"effort":2920.613749848464,"bugs":0.12481255341232751,"time":162.2563194360258},"params":1,"line":329,"cyclomaticDensity":23.076923076923077,"complexity":{"cyclomatic":3,"sloc":{"logical":13,"physical":33},"halstead":{"operators":{"distinct":10,"total":34,"identifiers":["__stripped__"]},"operands":{"distinct":25,"total":39,"identifiers":["__stripped__"]},"length":73,"vocabulary":35,"difficulty":7.800000000000001,"volume":374.43766023698254,"effort":2920.613749848464,"bugs":0.12481255341232751,"time":162.2563194360258}}},{"name":"xmlhttp.onreadystatechange","sloc":{"logical":6,"physical":9},"cyclomatic":2,"halstead":{"operators":{"distinct":6,"total":31,"identifiers":["__stripped__"]},"operands":{"distinct":19,"total":36,"identifiers":["__stripped__"]},"length":67,"vocabulary":25,"difficulty":5.684210526315789,"volume":311.1383647149065,"effort":1768.5759678531529,"bugs":0.10371278823830217,"time":98.25422043628627},"params":0,"line":350,"cyclomaticDensity":33.33333333333333,"complexity":{"cyclomatic":2,"sloc":{"logical":6,"physical":9},"halstead":{"operators":{"distinct":6,"total":31,"identifiers":["__stripped__"]},"operands":{"distinct":19,"total":36,"identifiers":["__stripped__"]},"length":67,"vocabulary":25,"difficulty":5.684210526315789,"volume":311.1383647149065,"effort":1768.5759678531529,"bugs":0.10371278823830217,"time":98.25422043628627}}},{"name":"showProjectResult","sloc":{"logical":13,"physical":29},"cyclomatic":3,"halstead":{"operators":{"distinct":10,"total":34,"identifiers":["__stripped__"]},"operands":{"distinct":25,"total":39,"identifiers":["__stripped__"]},"length":73,"vocabulary":35,"difficulty":7.800000000000001,"volume":374.43766023698254,"effort":2920.613749848464,"bugs":0.12481255341232751,"time":162.2563194360258},"params":1,"line":365,"cyclomaticDensity":23.076923076923077,"complexity":{"cyclomatic":3,"sloc":{"logical":13,"physical":29},"halstead":{"operators":{"distinct":10,"total":34,"identifiers":["__stripped__"]},"operands":{"distinct":25,"total":39,"identifiers":["__stripped__"]},"length":73,"vocabulary":35,"difficulty":7.800000000000001,"volume":374.43766023698254,"effort":2920.613749848464,"bugs":0.12481255341232751,"time":162.2563194360258}}},{"name":"xmlhttp.onreadystatechange","sloc":{"logical":6,"physical":9},"cyclomatic":2,"halstead":{"operators":{"distinct":6,"total":31,"identifiers":["__stripped__"]},"operands":{"distinct":19,"total":36,"identifiers":["__stripped__"]},"length":67,"vocabulary":25,"difficulty":5.684210526315789,"volume":311.1383647149065,"effort":1768.5759678531529,"bugs":0.10371278823830217,"time":98.25422043628627},"params":0,"line":382,"cyclomaticDensity":33.33333333333333,"complexity":{"cyclomatic":2,"sloc":{"logical":6,"physical":9},"halstead":{"operators":{"distinct":6,"total":31,"identifiers":["__stripped__"]},"operands":{"distinct":19,"total":36,"identifiers":["__stripped__"]},"length":67,"vocabulary":25,"difficulty":5.684210526315789,"volume":311.1383647149065,"effort":1768.5759678531529,"bugs":0.10371278823830217,"time":98.25422043628627}}},{"name":"get_tax_str","sloc":{"logical":7,"physical":21},"cyclomatic":2,"halstead":{"operators":{"distinct":8,"total":17,"identifiers":["__stripped__"]},"operands":{"distinct":15,"total":22,"identifiers":["__stripped__"]},"length":39,"vocabulary":23,"difficulty":5.866666666666666,"volume":176.41891628622352,"effort":1034.9909755458445,"bugs":0.05880630542874117,"time":57.49949864143581},"params":2,"line":397,"cyclomaticDensity":28.57142857142857,"complexity":{"cyclomatic":2,"sloc":{"logical":7,"physical":21},"halstead":{"operators":{"distinct":8,"total":17,"identifiers":["__stripped__"]},"operands":{"distinct":15,"total":22,"identifiers":["__stripped__"]},"length":39,"vocabulary":23,"difficulty":5.866666666666666,"volume":176.41891628622352,"effort":1034.9909755458445,"bugs":0.05880630542874117,"time":57.49949864143581}}},{"name":"xmlhttp.onreadystatechange","sloc":{"logical":7,"physical":10},"cyclomatic":2,"halstead":{"operators":{"distinct":7,"total":29,"identifiers":["__stripped__"]},"operands":{"distinct":17,"total":34,"identifiers":["__stripped__"]},"length":63,"vocabulary":24,"difficulty":7,"volume":288.8526375454329,"effort":2021.9684628180303,"bugs":0.09628421251514431,"time":112.33158126766835},"params":0,"line":405,"cyclomaticDensity":28.57142857142857,"complexity":{"cyclomatic":2,"sloc":{"logical":7,"physical":10},"halstead":{"operators":{"distinct":7,"total":29,"identifiers":["__stripped__"]},"operands":{"distinct":17,"total":34,"identifiers":["__stripped__"]},"length":63,"vocabulary":24,"difficulty":7,"volume":288.8526375454329,"effort":2021.9684628180303,"bugs":0.09628421251514431,"time":112.33158126766835}}}],"dependencies":[],"maintainability":57.885455661502036,"loc":14.235294117647058,"cyclomatic":2.823529411764706,"effort":4481.526069958336,"params":0.47058823529411764,"module":"public/javascripts/search.js"},"jshint":{"messages":[{"severity":"error","line":10,"column":61,"message":"Missing semicolon.","source":"Missing semicolon."},{"severity":"error","line":11,"column":62,"message":"Missing semicolon.","source":"Missing semicolon."},{"severity":"error","line":249,"column":20,"message":"Use '===' to compare with '0'.","source":"Use '{a}' to compare with '{b}'."},{"severity":"error","line":272,"column":25,"message":"Creating global 'for' variable. Should be 'for (var i ...'.","source":"Creating global 'for' variable. Should be 'for (var {a} ...'."},{"severity":"error","line":284,"column":10,"message":"Missing semicolon.","source":"Missing semicolon."},{"severity":"error","line":294,"column":17,"message":"Use '===' to compare with '0'.","source":"Use '{a}' to compare with '{b}'."},{"severity":"error","line":298,"column":64,"message":"Missing semicolon.","source":"Missing semicolon."},{"severity":"error","line":301,"column":65,"message":"Missing semicolon.","source":"Missing semicolon."},{"severity":"error","line":302,"column":66,"message":"Missing semicolon.","source":"Missing semicolon."},{"severity":"error","line":322,"column":4,"message":"Missing semicolon.","source":"Missing semicolon."},{"severity":"error","line":330,"column":17,"message":"Use '===' to compare with '0'.","source":"Use '{a}' to compare with '{b}'."},{"severity":"error","line":358,"column":4,"message":"Missing semicolon.","source":"Missing semicolon."},{"severity":"error","line":366,"column":17,"message":"Use '===' to compare with '0'.","source":"Use '{a}' to compare with '{b}'."},{"severity":"error","line":390,"column":4,"message":"Missing semicolon.","source":"Missing semicolon."},{"severity":"error","line":414,"column":6,"message":"Missing semicolon.","source":"Missing semicolon."}]}}